PLLParser.py
RETokenizer.py
TreeNode.py
parserUtils.py
PLLParser-0.3.3.dist-info/LICENSE
PLLParser-0.3.3.dist-info/METADATA
PLLParser-0.3.3.dist-info/WHEEL
PLLParser-0.3.3.dist-info/top_level.txt
PLLParser-0.3.3.dist-info/RECORD
