Metadata-Version: 2.1
Name: PLLParser
Version: 0.3.3
Summary: Parse a Python-like language
Home-page: https://github.com/johndeighan/PLLParser
Author: John Deighan
Author-email: john.deighan@gmail.com
License: MIT
Platform: UNKNOWN
Classifier: Programming Language :: Python :: 3
Classifier: License :: OSI Approved :: MIT License
Classifier: Operating System :: OS Independent
Requires-Python: >=3.6
